{
  "meta": {
    "id": "test3",
    "title": "Gastro_Intestinal_Tract_and_Hepatobiliary_Pancreas",
    "category": "Subject Wise / Mixed"
  },
  "questions": [
    {
      "text": "Match the following: Barium swallow a) 2.Barium meal b) 3.Barium follow through c) 4.Barium enema d)",
      "options": [
        {
          "label": "A",
          "text": "1-b, 2-d, 3-a, 4-c",
          "correct": false
        },
        {
          "label": "B",
          "text": "1-c, 2-a, 3-d, 4-b",
          "correct": true
        },
        {
          "label": "C",
          "text": "1-a, 2-c, 3-b, 4-d",
          "correct": false
        },
        {
          "label": "D",
          "text": "1-b, 2-a, 3-d, 4-c",
          "correct": false
        }
      ],
      "correct_answer": "B. 1-c, 2-a, 3-d, 4-b",
      "question_images": [
        "https://image.prepladder.com/notes/LtPdVec7F1IqaVg3l6YL1744085765.png",
        "https://image.prepladder.com/notes/oE93G5DUVXjxmLI2E5C61744085766.png",
        "https://image.prepladder.com/notes/kFUXv0FRg9RGRHoPMyhS1744085766.png",
        "https://image.prepladder.com/notes/b0ycsOzpmdupEO8zSRbf1744085766.png"
      ],
      "explanation_images": [
        "https://image.prepladder.com/notes/kFUXv0FRg9RGRHoPMyhS1744085766.png",
        "https://image.prepladder.com/notes/LtPdVec7F1IqaVg3l6YL1744085765.png",
        "https://image.prepladder.com/notes/b0ycsOzpmdupEO8zSRbf1744085766.png",
        "https://image.prepladder.com/notes/oE93G5DUVXjxmLI2E5C61744085766.png"
      ],
      "explanation": "<table cellspacing=\"0\" style=\"border-collapse:collapse; width:723px\">\n<tbody>\n<tr>\n<td colspan=\"2\" style=\"border-bottom:1px solid #000000; border-left:1px solid #000000; border-right:1px solid #000000; border-top:1px solid #000000; vertical-align:top\">\n<p><strong>Barium Studies</strong></p>\n</td>\n</tr>\n<tr>\n<td style=\"border-bottom:1px solid #000000; border-left:1px solid #000000; border-right:1px solid #000000; border-top:1px solid #000000; vertical-align:top\">\n<p><strong>Barium swallow</strong></p>\n<ul>\n<li>Test of the pharynx, esophagus, and <span class=\"customMeta\" data-dictid=\"bdbac654081692777196f9aab116f0\">proximal</span> stomach</li>\n<li>Contraindicated in any GI perforation- <span class=\"customMeta\" data-dictid=\"192677035a169277718780b4d6dbbb\">Esophageal</span> or intestinal and Tracheo-esophageal fistula</li>\n<li>There are three indentations in the <span class=\"customMeta\" data-dictid=\"6a729a105a169277718788389dbeab\">esophagus</span> :</li>\n<li>1st indentation- at the level of the Aortic Arch</li>\n<li>2nd indentation- at the level of Bronchus</li>\n<li>3rd indentation- at the level of the Left Atrium.</li>\n</ul>\n</td>\n<td style=\"border-bottom:1px solid #000000; border-left:1px solid #000000; border-right:1px solid #000000; border-top:1px solid #000000; vertical-align:top\"><img alt=\"-\" data-author=\" Ian Bickle\" data-hash=\"8096\" data-license=\"NA\" data-source=\"https://radiopaedia.org/cases/normal-barium-swallow#image-30793391\" data-tags=\"April2025\" src=\"https://image.prepladder.com/notes/kFUXv0FRg9RGRHoPMyhS1744085766.png\"/></td>\n</tr>\n<tr>\n<td style=\"border-bottom:1px solid #000000; border-left:1px solid #000000; border-right:1px solid #000000; border-top:1px solid #000000; vertical-align:top\">\n<p><strong>Barium meal</strong></p>\n<p>Tests the esophagus, stomach, and <span class=\"customMeta\" data-dictid=\"280e59e9331692777186f3beac2c41\">duodenum</span> (the first part of the small intestine)</p>\n</td>\n<td style=\"border-bottom:1px solid #000000; border-left:1px solid #000000; border-right:1px solid #000000; border-top:1px solid #000000; vertical-align:top\"><img alt=\"-\" data-author=\"\" data-hash=\"8094\" data-license=\"\" data-source=\"\" data-tags=\"April2025\" src=\"https://image.prepladder.com/notes/LtPdVec7F1IqaVg3l6YL1744085765.png\"/></td>\n</tr>\n<tr>\n<td style=\"border-bottom:1px solid #000000; border-left:1px solid #000000; border-right:1px solid #000000; border-top:1px solid #000000; vertical-align:top\">\n<p><strong>Barium follow through</strong></p>\n<ul>\n<li>Identify issues in the small <span class=\"customMeta\" data-dictid=\"7840cca3ed16927771901d2f6cb32b\">intestine</span> by <span class=\"customMeta\" data-dictid=\"ebb0986d331692777200ab09e1b2e8\">tracking</span> the passage of <span class=\"customMeta\" data-dictid=\"55052c0f0616927771829c99eec183\">barium</span> after ingestion.</li>\n<li>After drinking a <span class=\"customMeta\" data-dictid=\"55052c0f0616927771829c99eec183\">barium</span> liquid, there is a 10-15 minute wait before <span class=\"customMeta\" data-dictid=\"6fda63a90c1692777202563d33a81b\">X-rays</span> are taken every 30 minutes until the <span class=\"customMeta\" data-dictid=\"55052c0f0616927771829c99eec183\">barium</span> reaches the large intestine.</li>\n</ul>\n</td>\n<td style=\"border-bottom:1px solid #000000; border-left:1px solid #000000; border-right:1px solid #000000; border-top:1px solid #000000; vertical-align:top\"><img alt=\"-\" data-author=\"Subhan Iqbal\" data-hash=\"8097\" data-license=\"NA\" data-source=\" https://radiopaedia.org/articles/normal-oesophageal-contours-on-barium-swallow\" data-tags=\"April2025\" src=\"https://image.prepladder.com/notes/b0ycsOzpmdupEO8zSRbf1744085766.png\"/></td>\n</tr>\n<tr>\n<td style=\"border-bottom:1px solid #000000; border-left:1px solid #000000; border-right:1px solid #000000; border-top:1px solid #000000; vertical-align:top\">\n<p><strong>Barium enema</strong></p>\n<ul>\n<li>Barium is given Transrectally.</li>\n<li>Double-contrast (Barium + Air)\n\t\t\t\t<ul>\n<li>Positive contrast - <span class=\"customMeta\" data-dictid=\"55052c0f0616927771829c99eec183\">Barium</span> (white)</li>\n<li>Negative contrast - Air (black)</li>\n</ul>\n</li>\n<li>Tests the pathologies of the large intestine- rectum, <span class=\"customMeta\" data-dictid=\"9008060dc21692777198e329f5be75\">sigmoid</span> <span class=\"customMeta\" data-dictid=\"0fce15e71f1692777184feb9af5303\">colon</span> and ascending, <span class=\"customMeta\" data-dictid=\"a6260fa86416927772008d36bd7e5f\">transverse</span> and <span class=\"customMeta\" data-dictid=\"0cf8ac70611692777186b133d027f6\">descending</span> colon.</li>\n</ul>\n</td>\n<td style=\"border-bottom:1px solid #000000; border-left:1px solid #000000; border-right:1px solid #000000; border-top:1px solid #000000; vertical-align:top\"><img alt=\"-\" data-author=\"\" data-hash=\"8095\" data-license=\"\" data-source=\"\" data-tags=\"April2025\" src=\"https://image.prepladder.com/notes/oE93G5DUVXjxmLI2E5C61744085766.png\"/></td>\n</tr>\n</tbody>\n\n<p style='font-size: 10px; color: #808080; font-style: italic;'></p>",
      "bot": "@dams_new_robot",
      "audio": "https://image.prepladder.com/content/yO90LcYkrdXrPZJXdZCs1749046971.mp3",
      "video": "",
      "uid": "50a92a69"
    },
    {
      "text": "A 65-year-old man presents with sudden, severe abdominal pain and a rigid abdomen. He has a history of peptic ulcer disease. An erect chest X-ray is given below. Which of the following radiological signs is NOT expected in this case?",
      "options": [
        {
          "label": "A",
          "text": "Cupola sign",
          "correct": false
        },
        {
          "label": "B",
          "text": "Rigler\u2019s sign",
          "correct": false
        },
        {
          "label": "C",
          "text": "Free gas under the right hemidiaphragm",
          "correct": false
        },
        {
          "label": "D",
          "text": "Chilaiditi sign",
          "correct": true
        }
      ],
      "correct_answer": "D. Chilaiditi sign",
      "question_images": [
        "https://image.prepladder.com/notes/KWbY2YF1eml0WMLrj1GX1744085767.png"
      ],
      "explanation_images": [
        "https://image.prepladder.com/notes/nG3v64CmAZaaOqsJzBJm1744085768.png"
      ],
      "explanation": "<p style='font-size: 10px; color: #808080; font-style: italic;'></p>",
      "bot": "@dams_new_robot",
      "audio": "",
      "video": "",
      "uid": "f5eab823"
    },
    {
      "text": "A 72-year-old man presents with dysphagia, regurgitation, and halitosis. A barium swallow examination is performed which is given below. Which of the following radiological findings is most consistent with the presentation?",
      "options": [
        {
          "label": "A",
          "text": "An outpouching arising from the anterior wall of the proximal esophagus",
          "correct": false
        },
        {
          "label": "B",
          "text": "Multiple small diverticula along the length of the esophagus",
          "correct": false
        },
        {
          "label": "C",
          "text": "A diverticulum arising from the midline of the posterior wall of the distal pharynx",
          "correct": true
        },
        {
          "label": "D",
          "text": "A smooth narrowing of the distal esophagus",
          "correct": false
        }
      ],
      "correct_answer": "C. A diverticulum arising from the midline of the posterior wall of the distal pharynx",
      "question_images": [
        "https://image.prepladder.com/notes/RMZlJRGe20udE0BZvA0f1744086615.png"
      ],
      "explanation_images": [],
      "explanation": "<table cellspacing=\"0\" style=\"border-collapse:collapse; width:672px\">\n<tbody>\n<tr>\n<td style=\"border-bottom:1px solid #000000; border-left:1px solid #000000; border-right:1px solid #000000; border-top:1px solid #000000; vertical-align:top\">\n<p><strong>Imaging Modality</strong></p>\n</td>\n<td style=\"border-bottom:1px solid #000000; border-left:1px solid #000000; border-right:1px solid #000000; border-top:1px solid #000000; vertical-align:top\">\n<p><strong>Key Findings</strong></p>\n</td>\n</tr>\n<tr>\n<td style=\"border-bottom:1px solid #000000; border-left:1px solid #000000; border-right:1px solid #000000; border-top:1px solid #000000; vertical-align:top\">\n<p>Barium Swallow (Fluoroscopy)</p>\n</td>\n<td style=\"border-bottom:1px solid #000000; border-left:1px solid #000000; border-right:1px solid #000000; border-top:1px solid #000000; vertical-align:top\">\n<ul>\n<li>Diverticulum arising from the midline of the <span class=\"customMeta\" data-dictid=\"a5c6cb079d16927771967e62ffee72\">posterior</span> wall of the <span class=\"customMeta\" data-dictid=\"5ff25303a01692777186731f6a4f5c\">distal</span> pharynx</li>\n<li>Located near the <span class=\"customMeta\" data-dictid=\"0d9ab8e31b169277719584687d421a\">pharyngoesophageal</span> junction</li>\n<li>Best identified during swallowing</li>\n<li>Best seen on <span class=\"customMeta\" data-dictid=\"fc380e21321692777191739bd99191\">lateral</span> view</li>\n<li>Typically noted at the C5-6 level</li>\n<li>May be <span class=\"customMeta\" data-dictid=\"a6cf2c3dc51692777200ef7fb22f69\">transient</span> (referred to as a \"pharyngeal pouch\")</li>\n</ul>\n</td>\n</tr>\n<tr>\n<td style=\"border-bottom:1px solid #000000; border-left:1px solid #000000; border-right:1px solid #000000; border-top:1px solid #000000; vertical-align:top\">\n<p>Additional Findings</p>\n</td>\n<td style=\"border-bottom:1px solid #000000; border-left:1px solid #000000; border-right:1px solid #000000; border-top:1px solid #000000; vertical-align:top\">\n<ul>\n<li>~90% of patients also show a hiatal <span class=\"customMeta\" data-dictid=\"9cf1b2a8bc16927771899480554f5a\">hernia</span> and gastro-esophageal reflux</li>\n<li>The distended <span class=\"customMeta\" data-dictid=\"59ae5630de16927771988a866d1dea\">sac</span> may <span class=\"customMeta\" data-dictid=\"c6486470671692777184e25019e1f0\">compress</span> the <span class=\"customMeta\" data-dictid=\"25c6ce766c1692777184ab9a40305c\">cervical</span> esophagus</li>\n</ul>\n</td>\n</tr>\n</tbody>\n\n\n<p style='font-size: 10px; color: #808080; font-style: italic;'></p>",
      "bot": "@dams_new_robot",
      "audio": "",
      "video": "",
      "uid": "efc08f97"
    },
    {
      "text": "A 55-year-old patient presents with progressive dysphagia, initially for solids and later for liquids. A barium swallow study is performed, and two different radiographic findings are shown below. Which of the following statements correctly differentiates between these images?",
      "options": [
        {
          "label": "A",
          "text": "Image 1 shows achalasia cardia with a \"bird beak\" sign, while Image 2 shows carcinoma esophagus with irregular narrowing",
          "correct": true
        },
        {
          "label": "B",
          "text": "Image 1 shows carcinoma esophagus with smooth narrowing, while Image 2 shows achalasia cardia",
          "correct": false
        },
        {
          "label": "C",
          "text": "Both images show achalasia cardia",
          "correct": false
        },
        {
          "label": "D",
          "text": "Both images show carcinoma esophagus affecting different parts of the esophagus",
          "correct": false
        }
      ],
      "correct_answer": "A. Image 1 shows achalasia cardia with a \"bird beak\" sign, while Image 2 shows carcinoma esophagus with irregular narrowing",
      "question_images": [
        "https://image.prepladder.com/notes/5aOTl8fzgxVTRX7aFGMJ1744086616.png",
        "https://image.prepladder.com/notes/xZqt7euoT3x3cY6TRC3L1744086616.png"
      ],
      "explanation_images": [
        "https://image.prepladder.com/notes/dpIFYf6ME2XfgXD3vzop1744086617.png"
      ],
      "explanation": "<table cellspacing=\"0\" style=\"border-collapse:collapse; width:703px\">\n<tbody>\n<tr>\n<td style=\"border-bottom:1px solid #000000; border-left:1px solid #000000; border-right:1px solid #000000; border-top:1px solid #000000; vertical-align:top\">\n<p><strong>Feature</strong></p>\n</td>\n<td style=\"border-bottom:1px solid #000000; border-left:1px solid #000000; border-right:1px solid #000000; border-top:1px solid #000000; vertical-align:top\">\n<p><strong>Achalasia <span class=\"customMeta\" data-dictid=\"adc19c4a9b16927771836b8115874d\">Cardia</span> (Image 1) </strong><strong>(Option C)</strong></p>\n</td>\n<td style=\"border-bottom:1px solid #000000; border-left:1px solid #000000; border-right:1px solid #000000; border-top:1px solid #000000; vertical-align:top\">\n<p><strong>Carcinoma <span class=\"customMeta\" data-dictid=\"6a729a105a169277718788389dbeab\">Esophagus</span> (Image 2) </strong><strong>(Option D)</strong></p>\n</td>\n</tr>\n<tr>\n<td style=\"border-bottom:1px solid #000000; border-left:1px solid #000000; border-right:1px solid #000000; border-top:1px solid #000000; vertical-align:top\">\n<p><strong>Esophageal Appearance</strong></p>\n</td>\n<td style=\"border-bottom:1px solid #000000; border-left:1px solid #000000; border-right:1px solid #000000; border-top:1px solid #000000; vertical-align:top\">\n<p>Massively dilated esophagus</p>\n</td>\n<td style=\"border-bottom:1px solid #000000; border-left:1px solid #000000; border-right:1px solid #000000; border-top:1px solid #000000; vertical-align:top\">\n<p>Irregular narrowing of esophagus</p>\n</td>\n</tr>\n<tr>\n<td style=\"border-bottom:1px solid #000000; border-left:1px solid #000000; border-right:1px solid #000000; border-top:1px solid #000000; vertical-align:top\">\n<p><strong>Distal <span class=\"customMeta\" data-dictid=\"6a729a105a169277718788389dbeab\">Esophagus</span> </strong><strong>(Option B)</strong></p>\n</td>\n<td style=\"border-bottom:1px solid #000000; border-left:1px solid #000000; border-right:1px solid #000000; border-top:1px solid #000000; vertical-align:top\">\n<p>Narrow lower end (\"bird beak\" sign)</p>\n</td>\n<td style=\"border-bottom:1px solid #000000; border-left:1px solid #000000; border-right:1px solid #000000; border-top:1px solid #000000; vertical-align:top\">\n<p>Malignant stricture</p>\n</td>\n</tr>\n<tr>\n<td style=\"border-bottom:1px solid #000000; border-left:1px solid #000000; border-right:1px solid #000000; border-top:1px solid #000000; vertical-align:top\">\n<p><strong>Location</strong></p>\n</td>\n<td style=\"border-bottom:1px solid #000000; border-left:1px solid #000000; border-right:1px solid #000000; border-top:1px solid #000000; vertical-align:top\">\n<p>Affects lower <span class=\"customMeta\" data-dictid=\"192677035a169277718780b4d6dbbb\">esophageal</span> sphincter</p>\n</td>\n<td style=\"border-bottom:1px solid #000000; border-left:1px solid #000000; border-right:1px solid #000000; border-top:1px solid #000000; vertical-align:top\">\n<p>Mid-esophagus in this case</p>\n</td>\n</tr>\n<tr>\n<td style=\"border-bottom:1px solid #000000; border-left:1px solid #000000; border-right:1px solid #000000; border-top:1px solid #000000; vertical-align:top\">\n<p><strong>Contour</strong></p>\n</td>\n<td style=\"border-bottom:1px solid #000000; border-left:1px solid #000000; border-right:1px solid #000000; border-top:1px solid #000000; vertical-align:top\">\n<p>Smooth tapering at <span class=\"customMeta\" data-dictid=\"5ff25303a01692777186731f6a4f5c\">distal</span> end</p>\n</td>\n<td style=\"border-bottom:1px solid #000000; border-left:1px solid #000000; border-right:1px solid #000000; border-top:1px solid #000000; vertical-align:top\">\n<p>Irregular, abrupt narrowing</p>\n</td>\n</tr>\n<tr>\n<td style=\"border-bottom:1px solid #000000; border-left:1px solid #000000; border-right:1px solid #000000; border-top:1px solid #000000; vertical-align:top\">\n<p><strong>Additional Features</strong></p>\n</td>\n<td style=\"border-bottom:1px solid #000000; border-left:1px solid #000000; border-right:1px solid #000000; border-top:1px solid #000000; vertical-align:top\">\n<p>Proximal <span class=\"customMeta\" data-dictid=\"6a729a105a169277718788389dbeab\">esophagus</span> is dilated</p>\n</td>\n<td style=\"border-bottom:1px solid #000000; border-left:1px solid #000000; border-right:1px solid #000000; border-top:1px solid #000000; vertical-align:top\">\n<p>May show shouldering or \"apple core\" appearance (not visible in this image)</p>\n<p><img alt=\"-\" data-author=\"Roberto Rafael Ovalle\" data-hash=\"8110\" data-license=\"NA\" data-source=\"https://radiopaedia.org/cases/apple-core-sign\" data-tags=\"April2025\" src=\"https://image.prepladder.com/notes/dpIFYf6ME2XfgXD3vzop1744086617.png\"/><br/>\n<strong>Fig. Apple core appearance</strong></p>\n</td>\n</tr>\n</tbody>\n\n\n<p style='font-size: 10px; color: #808080; font-style: italic;'></p>",
      "bot": "@dams_new_robot",
      "audio": "https://image.prepladder.com/content/fWBU0brzH8Wb5mDwzpeS1749047943.mp3",
      "video": "",
      "uid": "e256fc4c"
    },
    {
      "text": "A 1-day-old newborn presents with respiratory distress. A chest X-ray is performed and is given below. Based on the findings, what is the most likely diagnosis?",
      "options": [
        {
          "label": "A",
          "text": "Congenital Diaphragmatic Hernia",
          "correct": true
        },
        {
          "label": "B",
          "text": "Esophageal atresia with tracheoesophageal fistula",
          "correct": false
        },
        {
          "label": "C",
          "text": "Pulmonary sequestration",
          "correct": false
        },
        {
          "label": "D",
          "text": "Congenital pulmonary airway malformation (CPAM)",
          "correct": false
        }
      ],
      "correct_answer": "A. Congenital Diaphragmatic Hernia",
      "question_images": [
        "https://image.prepladder.com/notes/ZMctUPxJdbyxsp3veInX1744087458.png"
      ],
      "explanation_images": [
        "https://image.prepladder.com/notes/ZMctUPxJdbyxsp3veInX1744087458.png",
        "https://image.prepladder.com/notes/fhoHFsogciEJS93RAzZi1744087459.png"
      ],
      "explanation": "<p style='font-size: 10px; color: #808080; font-style: italic;'></p>",
      "bot": "@dams_new_robot",
      "audio": "https://image.prepladder.com/content/Fn5HOE1sylw7g6S1nmQQ1745340954.mp3",
      "video": "",
      "uid": "3b15c836"
    },
    {
      "text": "A 65-year-old male presents with colicky abdominal pain, distension, vomiting, and absolute constipation for the past 48 hours. He has a history of prior abdominal surgery. On physical examination, his abdomen is distended with high-pitched bowel sounds. An abdominal X-ray is obtained and shows the following features. What is the most likely diagnosis based on the clinical presentation and radiographic findings?",
      "options": [
        {
          "label": "A",
          "text": "Small bowel obstruction",
          "correct": true
        },
        {
          "label": "B",
          "text": "Large bowel obstruction",
          "correct": false
        },
        {
          "label": "C",
          "text": "Sigmoid volvulus",
          "correct": false
        },
        {
          "label": "D",
          "text": "Paralytic ileus",
          "correct": false
        }
      ],
      "correct_answer": "A. Small bowel obstruction",
      "question_images": [
        "https://image.prepladder.com/notes/czAC6yztL2gsFCuy6uwR1749097353.jpeg"
      ],
      "explanation_images": [
        "https://image.prepladder.com/notes/NQtSekuqt7EyIvDYoxaI1744088611.png",
        "https://image.prepladder.com/notes/bBuJzp1N8QuZ6Lp6HQ7R1744088612.png",
        "https://image.prepladder.com/notes/CVBkBq9pxsR8dPesDyU11744088613.png",
        "https://image.prepladder.com/notes/pHpffXrI2QkkLbz5ortB1744088613.png"
      ],
      "explanation": "<table cellspacing=\"0\" style=\"border-collapse:collapse; width:650px\">\n<tbody>\n<tr>\n<td style=\"border-bottom:1px solid #000000; border-left:1px solid #000000; border-right:1px solid #000000; border-top:1px solid #000000; vertical-align:top\">\n<p><strong>Feature</strong></p>\n</td>\n<td style=\"border-bottom:1px solid #000000; border-left:1px solid #000000; border-right:1px solid #000000; border-top:1px solid #000000; vertical-align:top\">\n<p><strong>Small Bowel</strong></p>\n</td>\n<td style=\"border-bottom:1px solid #000000; border-left:1px solid #000000; border-right:1px solid #000000; border-top:1px solid #000000; vertical-align:top\">\n<p><strong>Large Bowel</strong></p>\n</td>\n</tr>\n<tr>\n<td style=\"border-bottom:1px solid #000000; border-left:1px solid #000000; border-right:1px solid #000000; border-top:1px solid #000000; vertical-align:top\">\n<p><strong>Number of loops</strong></p>\n</td>\n<td style=\"border-bottom:1px solid #000000; border-left:1px solid #000000; border-right:1px solid #000000; border-top:1px solid #000000; vertical-align:top\">\n<p>Many loops visible</p>\n</td>\n<td style=\"border-bottom:1px solid #000000; border-left:1px solid #000000; border-right:1px solid #000000; border-top:1px solid #000000; vertical-align:top\">\n<p>Few loops visible</p>\n</td>\n</tr>\n<tr>\n<td style=\"border-bottom:1px solid #000000; border-left:1px solid #000000; border-right:1px solid #000000; border-top:1px solid #000000; vertical-align:top\">\n<p><strong>Position of loops</strong></p>\n</td>\n<td style=\"border-bottom:1px solid #000000; border-left:1px solid #000000; border-right:1px solid #000000; border-top:1px solid #000000; vertical-align:top\">\n<p>Central abdomen</p>\n</td>\n<td style=\"border-bottom:1px solid #000000; border-left:1px solid #000000; border-right:1px solid #000000; border-top:1px solid #000000; vertical-align:top\">\n<p>Peripheral (framing the small bowel)</p>\n</td>\n</tr>\n<tr>\n<td style=\"border-bottom:1px solid #000000; border-left:1px solid #000000; border-right:1px solid #000000; border-top:1px solid #000000; vertical-align:top\">\n<p><strong>Wall/Mucosal pattern</strong></p>\n</td>\n<td style=\"border-bottom:1px solid #000000; border-left:1px solid #000000; border-right:1px solid #000000; border-top:1px solid #000000; vertical-align:top\">\n<p><strong>Valvulae conniventes</strong> (complete <span class=\"customMeta\" data-dictid=\"0919f0017e1692777184ac3748841f\">circular</span> folds)</p>\n</td>\n<td style=\"border-bottom:1px solid #000000; border-left:1px solid #000000; border-right:1px solid #000000; border-top:1px solid #000000; vertical-align:top\">\n<p><strong>Haustra </strong>(incomplete bands)</p>\n</td>\n</tr>\n<tr>\n<td style=\"border-bottom:1px solid #000000; border-left:1px solid #000000; border-right:1px solid #000000; border-top:1px solid #000000; vertical-align:top\">\n<p><strong>Diameter</strong></p>\n</td>\n<td style=\"border-bottom:1px solid #000000; border-left:1px solid #000000; border-right:1px solid #000000; border-top:1px solid #000000; vertical-align:top\">\n<p>>3 cm</p>\n</td>\n<td style=\"border-bottom:1px solid #000000; border-left:1px solid #000000; border-right:1px solid #000000; border-top:1px solid #000000; vertical-align:top\">\n<p>>6 cm (Caecum >9 cm)</p>\n</td>\n</tr>\n<tr>\n<td style=\"border-bottom:1px solid #000000; border-left:1px solid #000000; border-right:1px solid #000000; border-top:1px solid #000000; vertical-align:top\">\n<p><strong>Gas Pattern</strong></p>\n</td>\n<td style=\"border-bottom:1px solid #000000; border-left:1px solid #000000; border-right:1px solid #000000; border-top:1px solid #000000; vertical-align:top\">\n<p>Multiple air-fluid levels, <strong>\"string of beads\"</strong></p>\n</td>\n<td style=\"border-bottom:1px solid #000000; border-left:1px solid #000000; border-right:1px solid #000000; border-top:1px solid #000000; vertical-align:top\">\n<p>Distended colon, air-fluid levels</p>\n</td>\n</tr>\n<tr>\n<td style=\"border-bottom:1px solid #000000; border-left:1px solid #000000; border-right:1px solid #000000; border-top:1px solid #000000; vertical-align:top\">\u00a0</td>\n<td style=\"border-bottom:1px solid #000000; border-left:1px solid #000000; border-right:1px solid #000000; border-top:1px solid #000000; vertical-align:top\"><img alt=\"-\" data-author=\"Igboeze\" data-hash=\"8126\" data-license=\"CC BY SA 4.0\" data-source=\"https://commons.wikimedia.org/wiki/File:1._Bowel-obstruction-x-ray.jpg\" data-tags=\"April2025\" src=\"https://image.prepladder.com/notes/NQtSekuqt7EyIvDYoxaI1744088611.png\"/></td>\n<td style=\"border-bottom:1px solid #000000; border-left:1px solid #000000; border-right:1px solid #000000; border-top:1px solid #000000; vertical-align:top\"><img alt=\"-\" data-author=\"James Heilman\" data-hash=\"8127\" data-license=\"CC BY SA 3.0\" data-source=\"https://commons.wikimedia.org/wiki/File:LargeBowelObsFlat2008.jpg\" data-tags=\"April2025\" src=\"https://image.prepladder.com/notes/bBuJzp1N8QuZ6Lp6HQ7R1744088612.png\"/></td>\n</tr>\n</tbody>\n\n\n<p style='font-size: 10px; color: #808080; font-style: italic;'></p>",
      "bot": "@dams_new_robot",
      "audio": "",
      "video": "",
      "uid": "c6ed7a0b"
    },
    {
      "text": "A 7-year-old girl with a known history of lymphoma is brought to the emergency department for evaluation of severe abdominal pain and intermittent vomiting. Her parents report that she has recently passed currant jelly stools. On physical examination, a palpable abdominal mass is noted in the right upper quadrant. An abdominal ultrasound is given below. Based on the clinical presentation and the ultrasound findings, what is the most likely diagnosis?",
      "options": [
        {
          "label": "A",
          "text": "Acute appendicitis",
          "correct": false
        },
        {
          "label": "B",
          "text": "Intussusception",
          "correct": true
        },
        {
          "label": "C",
          "text": "Sigmoid Volvulus",
          "correct": false
        },
        {
          "label": "D",
          "text": "Cecal Volvulus",
          "correct": false
        }
      ],
      "correct_answer": "B. Intussusception",
      "question_images": [
        "https://image.prepladder.com/notes/2jLAf5nIEAIeEqZMtJwp1744089555.png"
      ],
      "explanation_images": [
        "https://image.prepladder.com/notes/35jQttNGRQdtatHDq3Sx1744089555.png",
        "https://image.prepladder.com/notes/bkx17w73cj6zab6A5peU1744089556.png",
        "https://image.prepladder.com/notes/VZI1oKU1eRyuq1p96ty61744089556.png"
      ],
      "explanation": "<p style='font-size: 10px; color: #808080; font-style: italic;'></p>",
      "bot": "@dams_new_robot",
      "audio": "",
      "video": "",
      "uid": "f78002fd"
    },
    {
      "text": "A 35-year-old male presents to the emergency department with chronic abdominal pain, fever, and unintentional weight loss over the past month. He reports altered bowel habits and has a history of exposure to individuals with tuberculosis. A small bowel follow-through imaging is provided below. Based on the clinical presentation and the attached imaging, which of the following features is not typically seen in the patient?",
      "options": [
        {
          "label": "A",
          "text": "Spasm and edema at the ileocecal valve",
          "correct": false
        },
        {
          "label": "B",
          "text": "Uniform thickening of the entire colon",
          "correct": true
        },
        {
          "label": "C",
          "text": "Presence of mesenteric adenopathy",
          "correct": false
        },
        {
          "label": "D",
          "text": "Stierlin Sign with rapid barium emptying",
          "correct": false
        }
      ],
      "correct_answer": "B. Uniform thickening of the entire colon",
      "question_images": [
        "https://image.prepladder.com/notes/eZlsWBY4IvhCpDSFVZXu1744089558.png"
      ],
      "explanation_images": [
        "https://image.prepladder.com/notes/1xfJCEMEXJddjdrjsl0p1744089558.png"
      ],
      "explanation": "<p><strong>References:</strong></p>\n<ul><li>\u21b3 David Sutton Textbook of Radiology and Imaging, Volume 1, 8th edition, Page 2254- 2258</li><li>\u21b3 Ileocecal tuberculosis | Radiology Reference Article | Radiopaedia.org</li></u\n<p style='font-size: 10px; color: #808080; font-style: italic;'></p>",
      "bot": "@dams_new_robot",
      "audio": "",
      "video": "",
      "uid": "f206884d"
    }
  ]
}